nonebot_plugin_zxwb/__init__.py
nonebot_plugin_zxwb/_command.py
nonebot_plugin_zxwb/_config.py
nonebot_plugin_zxwb/_data_source.py
nonebot_plugin_zxwb/_model.py
nonebot_plugin_zxwb/_rule.py
nonebot_plugin_zxwb/db_connect.py
nonebot_plugin_zxwb/exception.py
nonebot_plugin_zxwb/message_handle.py
nonebot_plugin_zxwb/read_word_bank.py
nonebot_plugin_zxwb/word_handle.py
nonebot_plugin_zxwb-0.1.7.dist-info/LICENSE
nonebot_plugin_zxwb-0.1.7.dist-info/METADATA
nonebot_plugin_zxwb-0.1.7.dist-info/WHEEL
nonebot_plugin_zxwb-0.1.7.dist-info/RECORD
