Metadata-Version: 2.1
Name: nonebot-plugin-zxwb
Version: 0.1.7
Summary: 
Author: HibiKier
Author-email: 775757368@qq.com
Requires-Python: >=3.10,<4.0
Classifier: Programming Language :: Python :: 3
Classifier: Programming Language :: Python :: 3.10
Classifier: Programming Language :: Python :: 3.11
Classifier: Programming Language :: Python :: 3.12
Requires-Dist: imagehash (>=4.3.1,<5.0.0)
Requires-Dist: nonebot-plugin-alconna (>=0.54.0,<0.55.0)
Requires-Dist: nonebot-plugin-localstore (>=0.7.2,<0.8.0)
Requires-Dist: nonebot-plugin-uninfo (>=0.6.0,<0.7.0)
Requires-Dist: nonebot2 (>=2.3.3,<3.0.0)
Requires-Dist: tortoise-orm (>=0.20.0,<0.21.0)
Requires-Dist: zhenxun-utils (>=0.1.2,<0.2.0)
